{"cameraMode":{"drawMode":0,"name":"Shaded","section":"Shading Mode"},"sceneLighting":true,"audioPlay":false,"sceneViewState":{"m_AlwaysRefresh":false,"showFog":true,"showSkybox":true,"showFlares":true,"showImageEffects":true,"showParticleSystems":true,"showVisualEffectGraphs":true,"m_FxEnabled":true},"in2DMode":false,"pivot":{"x":-420.74755859375,"y":34.71165084838867,"z":-248.02056884765626},"rotation":{"x":-0.08117497712373734,"y":-0.9136817455291748,"z":0.22653844952583314,"w":-0.32774707674980166},"size":63.24800109863281,"orthographic":false}